prescient/data/__init__.py
prescient/data/data_provider.py
prescient/data/data_provider_factory.py
prescient/data/providers/__init__.py
prescient/data/providers/dat_data_provider.py
prescient/data/providers/gmlc_data_provider.py
prescient/data/providers/shortcut_data_provider.py
prescient/data/simulation_state/__init__.py
prescient/data/simulation_state/_helper.py
prescient/data/simulation_state/mutable_simulation_state.py
prescient/data/simulation_state/simulation_state.py
prescient/data/simulation_state/state_with_offset.py
prescient/data/simulation_state/time_interpolated_state.py
prescient/downloaders/__init__.py
prescient/downloaders/rts_gmlc.py
prescient/downloaders/rts_gmlc_prescient/__init__.py
prescient/downloaders/rts_gmlc_prescient/process_RTS_GMLC_data.py
prescient/downloaders/rts_gmlc_prescient/rtsgmlc_to_dat.py
prescient/downloaders/rts_gmlc_prescient/runners/deterministic_scenario_creator_with_network.txt
prescient/downloaders/rts_gmlc_prescient/runners/populate_with_network_deterministic.txt
prescient/downloaders/rts_gmlc_prescient/runners/populate_with_network_deterministic_year.txt
prescient/downloaders/rts_gmlc_prescient/runners/simulate_with_network_deterministic.txt
prescient/downloaders/rts_gmlc_prescient/runners/simulate_with_network_deterministic_year.txt
prescient/downloaders/rts_gmlc_prescient/runners/sources_with_network.txt
prescient/downloaders/rts_gmlc_prescient/runners/templates/scenario_tree_template.dat
prescient/engine/__init__.py
prescient/engine/abstract_types.py
prescient/engine/data_extractors.py
prescient/engine/forecast_helper.py
prescient/engine/modeling_engine.py
prescient/engine/egret/__init__.py
prescient/engine/egret/data_extractors.py
prescient/engine/egret/egret_plugin.py
prescient/engine/egret/engine.py
prescient/engine/egret/ptdf_manager.py
prescient/engine/egret/reporting.py
prescient/gosm/basicclasses.py
prescient/gosm/benchmark.py
prescient/gosm/copula_test.py
prescient/gosm/exceptions.py
gridx_prescient-2.2.2.dist-info/LICENSE.txt
gridx_prescient-2.2.2.dist-info/METADATA
gridx_prescient-2.2.2.dist-info/WHEEL
gridx_prescient-2.2.2.dist-info/entry_points.txt
gridx_prescient-2.2.2.dist-info/top_level.txt
gridx_prescient-2.2.2.dist-info/RECORD
